LICENSE
assert_headers/HeaderAssertionError.py
assert_headers/__about__.py
assert_headers/__init__.py
assert_headers/__main__.py
assert_headers/assertHeaders.py
assert_headers/assertHeadersFromUrl.py
assert_headers/cli.py
assert_headers/getCLIConfiguration/__init__.py
assert_headers/getCLIConfiguration/getJsonConfiguration.py
assert_headers/getCLIConfiguration/getYamlConfiguration.py
assert_headers/getMeta.py
assert_headers-1.0.0.dist-info/entry_points.txt
assert_headers-1.0.0.dist-info/LICENSE
assert_headers-1.0.0.dist-info/WHEEL
assert_headers-1.0.0.dist-info/METADATA
assert_headers-1.0.0.dist-info/RECORD
