Metadata-Version: 2.1
Name: assert-headers
Version: 1.0.0
Summary: Assert HTTP headers.
Home-page: https://github.com/djragsdale/assert-headers-python
License: MIT
Keywords: http,https,headers,assert
Author: David Ragsdale
Author-email: pkgsupport@davidjragsdale.com
Requires-Python: >=3.8,<4.0
Classifier: License :: OSI Approved :: MIT License
Classifier: Programming Language :: Python :: 3
Classifier: Programming Language :: Python :: 3.8
Classifier: Programming Language :: Python :: 3.9
Requires-Dist: PyYAML (>=5.4.1,<6.0.0)
Requires-Dist: requests (>=2.25.1,<3.0.0)
Project-URL: Repository, https://github.com/djragsdale/assert-headers-python
